solid_scorer.py
dip/__init__.py
dip/core.py
dip/facade.py
dip/protocols.py
isp/__init__.py
isp/core.py
isp/facade.py
isp/protocols.py
lsp/__init__.py
lsp/core.py
lsp/facade.py
lsp/protocols.py
ocp/__init__.py
ocp/core.py
ocp/facade.py
ocp/protocols.py
solid_checker-1.0.4.dist-info/licenses/LICENSE
solid_core/__init__.py
solid_core/analyzer.py
solid_core/models.py
solid_core/project_analysis.py
solid_core/reports.py
solid_core/scorer.py
solid_core/smart_analysis.py
srp/__init__.py
srp/core.py
srp/facade.py
srp/protocols.py
solid_checker-1.0.4.dist-info/METADATA
solid_checker-1.0.4.dist-info/WHEEL
solid_checker-1.0.4.dist-info/entry_points.txt
solid_checker-1.0.4.dist-info/top_level.txt
solid_checker-1.0.4.dist-info/RECORD
