Metadata-Version: 2.4
Name: solid-checker
Version: 1.0.4
Summary: Smart SOLID principles analyzer with context-aware scoring and adaptive recommendations
Author-email: DaymaNKinG990 <xellaopromaster@yandex.ru>
License-Expression: MIT
Project-URL: Homepage, https://github.com/DaymaNKinG990/solid-checker
Project-URL: Repository, https://github.com/DaymaNKinG990/solid-checker.git
Project-URL: Documentation, https://github.com/DaymaNKinG990/solid-checker#readme
Project-URL: Issues, https://github.com/DaymaNKinG990/solid-checker/issues
Keywords: solid,principles,code-analysis,static-analysis,architecture,clean-code
Classifier: Development Status :: 5 - Production/Stable
Classifier: Environment :: Console
Classifier: Intended Audience :: Developers
Classifier: Operating System :: OS Independent
Classifier: Programming Language :: Python :: 3
Classifier: Programming Language :: Python :: 3.10
Classifier: Programming Language :: Python :: 3.11
Classifier: Programming Language :: Python :: 3.12
Classifier: Programming Language :: Python :: 3.13
Classifier: Topic :: Software Development :: Quality Assurance
Classifier: Topic :: Software Development :: Libraries :: Python Modules
Classifier: Typing :: Typed
Requires-Python: >=3.10
License-File: LICENSE
Provides-Extra: dev
Requires-Dist: ruff>=0.1.0; extra == "dev"
Requires-Dist: mypy>=1.7.0; extra == "dev"
Dynamic: license-file
